xtr/__init__.py
xtr/_modidx.py
xtr/args.py
xtr/atyp.py
xtr/call.py
xtr/itrs.py
xtr/load.py
xtr/misc.py
xtr/posx.py
xtr/strs.py
xtr/tups.py
xtr/util.py
xtr-0.0.7.dist-info/LICENSE
xtr-0.0.7.dist-info/METADATA
xtr-0.0.7.dist-info/WHEEL
xtr-0.0.7.dist-info/entry_points.txt
xtr-0.0.7.dist-info/top_level.txt
xtr-0.0.7.dist-info/RECORD
